{
  "type": "FeatureCollection",
  "features": [
    {
      "type": "Feature",
      "geometry": {
        "type": "Point",
        "coordinates": [
          18.464715,
          54.471741
        ]
      },
      "properties": {
        "title": "Mój blok",
        "description": "Tyb architektury Barok Stalinowski",
        "marker-size": "medium",
        "marker-symbol": "building"
      }
    },
    {
      "type": "Feature",
      "geometry": {
        "type": "Point",
        "coordinates": [
          17.7462722,
          54.5322331
        ]
      },
      "properties": {
        "title": "Tu się urodziłem",
        "description": "SPS ZOZ Lębork",
        "marker-size": "medium",
        "marker-symbol": "Hospital"
      }
    },
    {
      "type": "Feature",
      "geometry": {
        "type": "Point",
        "coordinates": [
          18.321744800000033,
          54.82624509999999
        ]
      },
      "properties": {
        "title": "Tu odpoczywam",
        "description": "K.D.W. Magnolia",
        "marker-size": "medium",
        "marker-symbol": "lighthouse"
      }
    },
    {
      "type": "Feature",
      "geometry": {
        "type": "Point",
        "coordinates": [
          18.573444,
          54.395736
        ]
      },
      "properties": {
        "title": "Tu się uczę",
        "description": "U.G. Instytut Informatyki",
        "marker-size": "medium",
        "marker-symbol": "college"
      }
    }
  ]
}
