{
  "type": "FeatureCollection",
  "features": [
    {
      "type": "Feature",
      "geometry": {
        "type": "Point",
        "coordinates": [
          54.471826,
          18.4627209,
        ]
      },
      "properties": {
        "title": "Mój blok",
        "description": "Tyb architektury Barok Stalinowski",
        "marker-size": "medium",
        "marker-symbol": "home"
      }
    },
    {
