{
  "type": "FeatureCollection",
  "features": [
    {
      "type": "Feature",
      "geometry": {
        "type": "Point",
        "coordinates": [
          18.464715,
          54.471741
        ]
      },
      "properties": {
        "title": "Mój blok",
        "description": "Tyb architektury Barok Stalinowski",
        "marker-size": "medium",
        "marker-symbol": "building"
      }
    },
    {
      "type": "Feature",
      "geometry": {
        "type": "Point",
        "coordinates": [
          18.321744800000033,
          54.82624509999999
        ]
      },
      "properties": {
        "title": "Tu odpoczywam",
        "description": "K.D.W. Magnolia",
        "marker-size": "medium",
        "marker-symbol": "hotel"
      }
    }
  ]
}
