{
  "type": "FeatureCollection",
  "features": [
    {
      "type": "Feature",
      "geometry": {
        "type": "Point",
        "coordinates": [
          17.0400009155,
          52.3219985962
        ]
      },
      "properties": {
        "title": "Mój blok",
        "description": "Tyb architektury Barok Stalinowski",
        "marker-size": "medium",
        "marker-symbol": "Lotnisko"
      }
    }
  ]
}
