{
  "type": "FeatureCollection",
  "features": [
    {
      "type": "Feature",
      "geometry": {
        "type": "Point",
        "coordinates": [
          18.464715,
          54.471741
        ]
      },
      "properties": {
        "title": "Mój blok",
        "description": "Tyb architektury Barok Stalinowski",
        "marker-size": "large",
        "marker-symbol": "building"
      }
    }
  ]
}
